csiread/utils.py
csiread/_csiread.cpython-313-x86_64-linux-gnu.so
csiread/core.py
csiread/__init__.py
csiread/_type.py
csiread/_picoscenes.cpython-313-x86_64-linux-gnu.so
csiread-1.4.1.dist-info/METADATA
csiread-1.4.1.dist-info/LICENSE.md
csiread-1.4.1.dist-info/WHEEL
csiread-1.4.1.dist-info/top_level.txt
csiread-1.4.1.dist-info/RECORD
