Metadata-Version: 2.1
Name: csiread
Version: 1.4.1
Summary: A **fast** channel state information parser for Intel, Atheros, Nexmon, ESP32 and PicoScenes in Python.
Home-page: https://github.com/citysu/csiread
Author: Hecheng Su
Author-email: 2215523266@qq.com
License: MIT
Classifier: Topic :: Scientific/Engineering
Classifier: Programming Language :: Python :: 3
Classifier: Programming Language :: Python :: Implementation :: CPython
Classifier: Operating System :: Unix
Classifier: Operating System :: POSIX
Classifier: Operating System :: Microsoft
Classifier: Operating System :: MacOS
Classifier: License :: OSI Approved :: MIT License
Requires-Python: >=3
License-File: LICENSE.md
Requires-Dist: numpy
